main.py
alex_mcp_weather_server-0.1.1.dist-info/METADATA
alex_mcp_weather_server-0.1.1.dist-info/WHEEL
alex_mcp_weather_server-0.1.1.dist-info/entry_points.txt
alex_mcp_weather_server-0.1.1.dist-info/top_level.txt
alex_mcp_weather_server-0.1.1.dist-info/RECORD
