Metadata-Version: 2.4
Name: alex-mcp-weather-server
Version: 0.1.1
Summary: 输入OpenWeather-API-KEY，获取天气信息
Requires-Python: >=3.12
Requires-Dist: httpx>=0.28.1
Requires-Dist: mcp[cli]>=1.7.0
